easyseries/__init__.py
easyseries/cli/__init__.py
easyseries/cli/main.py
easyseries/core/__init__.py
easyseries/core/config.py
easyseries/core/exceptions.py
easyseries/http/__init__.py
easyseries/http/client.py
easyseries/http/utils.py
easyseries-0.1.3.dist-info/METADATA
easyseries-0.1.3.dist-info/WHEEL
easyseries-0.1.3.dist-info/entry_points.txt
easyseries-0.1.3.dist-info/licenses/LICENSE
easyseries-0.1.3.dist-info/RECORD
